LICENSE
MANIFEST.in
README.rst
setup.py
upload.bat
radware_os_lb_v2_mitaka/__init__.py
radware_os_lb_v2_mitaka/another_lbaas_driver.py
radware_os_lb_v2_mitaka/base_driver.py
radware_os_lb_v2_mitaka/config.py
radware_os_lb_v2_mitaka/exceptions.py
radware_os_lb_v2_mitaka/radware_lbaas_driver.py
radware_os_lb_v2_mitaka/rest_client.py
radware_os_lb_v2_mitaka.egg-info/PKG-INFO
radware_os_lb_v2_mitaka.egg-info/SOURCES.txt
radware_os_lb_v2_mitaka.egg-info/dependency_links.txt
radware_os_lb_v2_mitaka.egg-info/not-zip-safe
radware_os_lb_v2_mitaka.egg-info/top_level.txt